dashc/__about__.py
dashc/__init__.py
dashc/__main__.py
dashc/core.py
dashc/custom_exceptions.py
dashc/plain_text.py
dashc/single_file.py
dashc/single_module.py
dashc/validate_syntax.py
dashc/templates/wrapper.py.j2
dashc/templates/wrapper_plain.py.j2
dashc/templates/wrapper_zip.py.j2
dashc/templates/wrapper_zip_with_data.py.j2
dashc/utils/__init__.py
dashc/utils/cli_suggestions.py
dashc-0.1.1.dist-info/METADATA
dashc-0.1.1.dist-info/WHEEL
dashc-0.1.1.dist-info/entry_points.txt
dashc-0.1.1.dist-info/licenses/AUTHORS.md
dashc-0.1.1.dist-info/licenses/LICENSE
dashc-0.1.1.dist-info/RECORD
