Metadata-Version: 2.4
Name: dashc
Version: 0.1.1
Summary: Tool to generate python -c bash as if it were a package format.
Project-URL: Repository, https://github.com/matthewdeanmartin/dashc
Project-URL: Changelog, https://github.com/matthewdeanmartin/dashc/blob/main/CHANGELOG.md
Project-URL: homepage, https://github.com/matthewdeanmartin/dashc
Project-URL: issues, https://github.com/matthewdeanmartin/dashc/issues/
Author-email: Matthew Martin <matthewdeanmartin@gmail.com>
License-File: AUTHORS.md
License-File: LICENSE
Keywords: bash,packaging
Classifier: Development Status :: 4 - Beta
Classifier: Intended Audience :: Developers
Classifier: License :: OSI Approved :: MIT License
Classifier: Operating System :: OS Independent
Classifier: Programming Language :: Python
Classifier: Programming Language :: Python :: 3.8
Classifier: Programming Language :: Python :: 3.9
Classifier: Programming Language :: Python :: 3.10
Classifier: Programming Language :: Python :: 3.11
Classifier: Programming Language :: Python :: 3.12
Classifier: Programming Language :: Python :: 3.13
Classifier: Programming Language :: Python :: 3.14
Requires-Python: >=3.8
Requires-Dist: argcomplete
Requires-Dist: jinja2
Requires-Dist: orjson
